kisstdlib/__init__.py
kisstdlib/argparse_ext.py
kisstdlib/base.py
kisstdlib/compression.py
kisstdlib/failure.py
kisstdlib/fs.py
kisstdlib/getpass_ext.py
kisstdlib/itertools_ext.py
kisstdlib/logging_ext.py
kisstdlib/parsing.py
kisstdlib/py.typed
kisstdlib/pyrepr.py
kisstdlib/signal_ext.py
kisstdlib/sorted.py
kisstdlib/sqlite3_ext.py
kisstdlib/string_ext.py
kisstdlib/tariter.py
kisstdlib/time.py
kisstdlib/io/__init__.py
kisstdlib/io/adapter.py
kisstdlib/io/base.py
kisstdlib/io/encoder.py
kisstdlib/io/stdio.py
kisstdlib/io/wrapper.py
kisstdlib_bin/describe_forest.py
kisstdlib-0.0.12.dist-info/LICENSE.txt
kisstdlib-0.0.12.dist-info/METADATA
kisstdlib-0.0.12.dist-info/WHEEL
kisstdlib-0.0.12.dist-info/entry_points.txt
kisstdlib-0.0.12.dist-info/top_level.txt
kisstdlib-0.0.12.dist-info/RECORD
