Metadata-Version: 2.2
Name: kisstdlib
Version: 0.0.12
Summary: System programming with conceptually and algebraically simple primitives.
Author-email: Jan Malakhovski <oxij@oxij.org>
Project-URL: Homepage, https://oxij.org/software/kisstdlib/
Project-URL: GitHub, https://github.com/oxij/kisstdlib
Project-URL: Support Development, https://oxij.org/#support
Keywords: sys,stdlib
Classifier: Development Status :: 4 - Beta
Classifier: Programming Language :: Python :: 3
Classifier: License :: OSI Approved :: MIT License
Classifier: License :: OSI Approved :: Python Software Foundation License
Classifier: License :: OSI Approved :: BSD License
Requires-Python: >=3.11
License-File: LICENSE.txt
Requires-Dist: sortedcontainers==2.4.*
